odoo8_addon_mass_mailing_partner-8.0.2.1.0-py2.7-nspkg.pth
odoo_addons/mass_mailing_partner/__openerp__.py
odoo_addons/mass_mailing_partner/hooks.py
odoo_addons/mass_mailing_partner/__init__.py
odoo_addons/mass_mailing_partner/README.rst
odoo_addons/mass_mailing_partner/models/res_partner.py
odoo_addons/mass_mailing_partner/models/mail_mass_mailing_contact.py
odoo_addons/mass_mailing_partner/models/mail_mail_statistics.py
odoo_addons/mass_mailing_partner/models/__init__.py
odoo_addons/mass_mailing_partner/models/mail_mass_mailing.py
odoo_addons/mass_mailing_partner/i18n/mass_mailing_partner.pot
odoo_addons/mass_mailing_partner/i18n/it.po
odoo_addons/mass_mailing_partner/i18n/es.po
odoo_addons/mass_mailing_partner/i18n/hr.po
odoo_addons/mass_mailing_partner/i18n/sl.po
odoo_addons/mass_mailing_partner/i18n/nl.po
odoo_addons/mass_mailing_partner/i18n/fr.po
odoo_addons/mass_mailing_partner/i18n/pt_BR.po
odoo_addons/mass_mailing_partner/wizard/partner_mail_list_wizard.py
odoo_addons/mass_mailing_partner/wizard/__init__.py
odoo_addons/mass_mailing_partner/wizard/partner_mail_list_wizard.xml
odoo_addons/mass_mailing_partner/views/mail_mass_mailing_contact_view.xml
odoo_addons/mass_mailing_partner/views/res_partner_view.xml
odoo_addons/mass_mailing_partner/views/mail_mail_statistics_view.xml
odoo_addons/mass_mailing_partner/views/mail_mass_mailing_view.xml
odoo_addons/mass_mailing_partner/tests/test_mail_mail_statistics.py
odoo_addons/mass_mailing_partner/tests/test_partner_mail_list_wizard.py
odoo_addons/mass_mailing_partner/tests/__init__.py
odoo_addons/mass_mailing_partner/tests/test_mail_mass_mailing_contact.py
odoo_addons/mass_mailing_partner/tests/test_res_partner.py
odoo_addons/mass_mailing_partner/tests/base.py
odoo_addons/mass_mailing_partner/static/description/icon.png
odoo8_addon_mass_mailing_partner-8.0.2.1.0.dist-info/top_level.txt
odoo8_addon_mass_mailing_partner-8.0.2.1.0.dist-info/WHEEL
odoo8_addon_mass_mailing_partner-8.0.2.1.0.dist-info/RECORD
odoo8_addon_mass_mailing_partner-8.0.2.1.0.dist-info/metadata.json
odoo8_addon_mass_mailing_partner-8.0.2.1.0.dist-info/DESCRIPTION.rst
odoo8_addon_mass_mailing_partner-8.0.2.1.0.dist-info/METADATA
odoo8_addon_mass_mailing_partner-8.0.2.1.0.dist-info/namespace_packages.txt
